phink/__init__.py
phink/build.py
phink/cli.py
phink/init.py
phink/serve.py
phink/templates/README.md
phink/templates/api.md
phink/templates/commands.md
phink/templates/conf.py
phink/templates/customising.md
phink/templates/index.rst
phink/templates/module.py
phink-0.2.0.dist-info/entry_points.txt
phink-0.2.0.dist-info/LICENSE.txt
phink-0.2.0.dist-info/WHEEL
phink-0.2.0.dist-info/METADATA
phink-0.2.0.dist-info/RECORD
