Metadata-Version: 2.1
Name: phink
Version: 0.2.0
Summary: Phink provides a convenient wrapper around Sphinx to make project documentation a breeze.
Home-page: https://github.com/sneakypete81/clickshot
License: GPL-3.0
Keywords: documentation,sphinx,readthedocs
Author: sneakypete81
Author-email: sneakypete81@gmail.com
Requires-Python: >=3.6,<4.0
Classifier: Development Status :: 4 - Beta
Classifier: Framework :: Sphinx
Classifier: Intended Audience :: Developers
Classifier: License :: OSI Approved :: GNU General Public License v3 (GPLv3)
Classifier: Programming Language :: Python :: 3
Classifier: Programming Language :: Python :: 3.6
Classifier: Programming Language :: Python :: 3.7
Classifier: Topic :: Documentation
Classifier: Topic :: Documentation :: Sphinx
Classifier: Topic :: Software Development :: Documentation
Classifier: Topic :: Text Processing :: Markup :: HTML
Requires-Dist: livereload (>=2.6,<3.0)
Requires-Dist: recommonmark (>=0.6.0,<0.7.0)
Requires-Dist: sphinx (>=2.2,<3.0)
Requires-Dist: sphinx_rtd_theme (>=0.4.3,<0.5.0)
Project-URL: Repository, https://github.com/sneakypete81/clickshot
